pytest_perf/deco.py
pytest_perf/plugin.py
pytest_perf/runner.py
pytest_perf/compat/__init__.py
pytest_perf/compat/py38.py
pytest_perf-0.15.0.dist-info/LICENSE
pytest_perf-0.15.0.dist-info/METADATA
pytest_perf-0.15.0.dist-info/WHEEL
pytest_perf-0.15.0.dist-info/entry_points.txt
pytest_perf-0.15.0.dist-info/top_level.txt
pytest_perf-0.15.0.dist-info/RECORD
