Metadata-Version: 2.1
Name: pytest-perf
Version: 0.15.0
Summary: Run performance tests against the mainline code.
Author-email: "Jason R. Coombs" <jaraco@jaraco.com>
Project-URL: Homepage, https://github.com/jaraco/pytest-perf
Classifier: Development Status :: 5 - Production/Stable
Classifier: Intended Audience :: Developers
Classifier: License :: OSI Approved :: MIT License
Classifier: Programming Language :: Python :: 3
Classifier: Programming Language :: Python :: 3 :: Only
Requires-Python: >=3.8
License-File: LICENSE
Requires-Dist: pip-run >=8.5
Requires-Dist: tempora >=4.1
Requires-Dist: jaraco.functools
Requires-Dist: more-itertools
Requires-Dist: jaraco.context
Requires-Dist: packaging
Provides-Extra: docs
Requires-Dist: sphinx >=3.5 ; extra == 'docs'
Requires-Dist: jaraco.packaging >=9.3 ; extra == 'docs'
Requires-Dist: rst.linker >=1.9 ; extra == 'docs'
Requires-Dist: furo ; extra == 'docs'
Requires-Dist: sphinx-lint ; extra == 'docs'
Provides-Extra: testing
Requires-Dist: pytest !=8.1.*,>=6 ; extra == 'testing'
Requires-Dist: pytest-checkdocs >=2.4 ; extra == 'testing'
Requires-Dist: pytest-cov ; extra == 'testing'
Requires-Dist: pytest-mypy ; extra == 'testing'
Requires-Dist: pytest-enabler >=2.2 ; extra == 'testing'
Requires-Dist: pytest-ruff >=0.2.1 ; extra == 'testing'
Requires-Dist: pytest-subprocess ; extra == 'testing'
